<annotation>
	<folder>RosData</folder>
	<filename>frame0039.jpg</filename>
	<path>/Users/suhailamp/Desktop/MS2/CudaVision/Cuda-Vision-Lab/Project/RosData/frame0039.jpg</path>
	<source>
		<database>Unknown</database>
	</source>
	<size>
		<width>640</width>
		<height>480</height>
		<depth>3</depth>
	</size>
	<segmented>0</segmented>
	<object>
		<name>goalpost</name>
		<pose>Unspecified</pose>
		<truncated>0</truncated>
		<difficult>0</difficult>
		<bndbox>
			<xmin>284</xmin>
			<ymin>130</ymin>
			<xmax>312</xmax>
			<ymax>157</ymax>
		</bndbox>
	</object>
	<object>
		<name>goalpost</name>
		<pose>Unspecified</pose>
		<truncated>0</truncated>
		<difficult>0</difficult>
		<bndbox>
			<xmin>417</xmin>
			<ymin>143</ymin>
			<xmax>445</xmax>
			<ymax>169</ymax>
		</bndbox>
	</object>
	<object>
		<name>robot</name>
		<pose>Unspecified</pose>
		<truncated>0</truncated>
		<difficult>0</difficult>
		<bndbox>
			<xmin>373</xmin>
			<ymin>191</ymin>
			<xmax>418</xmax>
			<ymax>227</ymax>
		</bndbox>
	</object>
</annotation>
